deq_tools/__init__.py
deq_tools-0.2.1.dist-info/LICENSE.md
deq_tools-0.2.1.dist-info/METADATA
deq_tools-0.2.1.dist-info/WHEEL
deq_tools-0.2.1.dist-info/top_level.txt
deq_tools-0.2.1.dist-info/RECORD
