Metadata-Version: 2.1
Name: deq-tools
Version: 0.2.1
Summary: Tools for downloading Oregon DEQ Air Quality data
Home-page: https://github.com/eykamp/deq_tools
Author: Chris Eykamp
Author-email: chris@eykamp.com
License: MIT
Download-URL: https://github.com/eykamp/deq_tools/archive/v0.2.0.tar.gz
Keywords: deq,airquality,data
Platform: UNKNOWN
Classifier: Programming Language :: Python :: 3
Classifier: License :: OSI Approved :: MIT License
Classifier: Operating System :: OS Independent
Requires-Dist: requests
Requires-Dist: pydantic
Requires-Dist: tenacity
